{
  "_comment": "code automatically generated by pycrate_asn1c",
  "nodes": [
    {"id": "_IMPL_.REAL", "group": 0},
    {"id": "_IMPL_.EXTERNAL", "group": 0},
    {"id": "_IMPL_.EMBEDDED PDV", "group": 0},
    {"id": "_IMPL_.CHARACTER STRING", "group": 0},
    {"id": "_IMPL_.TYPE-IDENTIFIER", "group": 0},
    {"id": "_IMPL_.ABSTRACT-SYNTAX", "group": 0},
    {"id": "DENM-PDU-Descriptions.DENM", "group": 2},
    {"id": "DENM-PDU-Descriptions.DecentralizedEnvironmentalNotificationMessage", "group": 2},
    {"id": "DENM-PDU-Descriptions.ManagementContainer", "group": 2},
    {"id": "DENM-PDU-Descriptions.SituationContainer", "group": 2},
    {"id": "DENM-PDU-Descriptions.LocationContainer", "group": 2},
    {"id": "DENM-PDU-Descriptions.ImpactReductionContainer", "group": 2},
    {"id": "DENM-PDU-Descriptions.RoadWorksContainerExtended", "group": 2},
    {"id": "DENM-PDU-Descriptions.StationaryVehicleContainer", "group": 2},
    {"id": "DENM-PDU-Descriptions.AlacarteContainer", "group": 2},
    {"id": "DENM-PDU-Descriptions.defaultValidity", "group": 2},
    {"id": "DENM-PDU-Descriptions.Termination", "group": 2},
    {"id": "DENM-PDU-Descriptions.ReferenceDenms", "group": 2},
    {"id": "ITS-Container.ItsPduHeader", "group": 3},
    {"id": "ITS-Container.StationID", "group": 3},
    {"id": "ITS-Container.ReferencePosition", "group": 3},
    {"id": "ITS-Container.DeltaReferencePosition", "group": 3},
    {"id": "ITS-Container.Longitude", "group": 3},
    {"id": "ITS-Container.Latitude", "group": 3},
    {"id": "ITS-Container.Altitude", "group": 3},
    {"id": "ITS-Container.AltitudeValue", "group": 3},
    {"id": "ITS-Container.AltitudeConfidence", "group": 3},
    {"id": "ITS-Container.DeltaLongitude", "group": 3},
    {"id": "ITS-Container.DeltaLatitude", "group": 3},
    {"id": "ITS-Container.DeltaAltitude", "group": 3},
    {"id": "ITS-Container.PosConfidenceEllipse", "group": 3},
    {"id": "ITS-Container.PathPoint", "group": 3},
    {"id": "ITS-Container.PathDeltaTime", "group": 3},
    {"id": "ITS-Container.PtActivation", "group": 3},
    {"id": "ITS-Container.PtActivationType", "group": 3},
    {"id": "ITS-Container.PtActivationData", "group": 3},
    {"id": "ITS-Container.AccelerationControl", "group": 3},
    {"id": "ITS-Container.SemiAxisLength", "group": 3},
    {"id": "ITS-Container.CauseCode", "group": 3},
    {"id": "ITS-Container.CauseCodeType", "group": 3},
    {"id": "ITS-Container.SubCauseCodeType", "group": 3},
    {"id": "ITS-Container.TrafficConditionSubCauseCode", "group": 3},
    {"id": "ITS-Container.AccidentSubCauseCode", "group": 3},
    {"id": "ITS-Container.RoadworksSubCauseCode", "group": 3},
    {"id": "ITS-Container.HumanPresenceOnTheRoadSubCauseCode", "group": 3},
    {"id": "ITS-Container.WrongWayDrivingSubCauseCode", "group": 3},
    {"id": "ITS-Container.AdverseWeatherCondition-ExtremeWeatherConditionSubCauseCode", "group": 3},
    {"id": "ITS-Container.AdverseWeatherCondition-AdhesionSubCauseCode", "group": 3},
    {"id": "ITS-Container.AdverseWeatherCondition-VisibilitySubCauseCode", "group": 3},
    {"id": "ITS-Container.AdverseWeatherCondition-PrecipitationSubCauseCode", "group": 3},
    {"id": "ITS-Container.SlowVehicleSubCauseCode", "group": 3},
    {"id": "ITS-Container.StationaryVehicleSubCauseCode", "group": 3},
    {"id": "ITS-Container.HumanProblemSubCauseCode", "group": 3},
    {"id": "ITS-Container.EmergencyVehicleApproachingSubCauseCode", "group": 3},
    {"id": "ITS-Container.HazardousLocation-DangerousCurveSubCauseCode", "group": 3},
    {"id": "ITS-Container.HazardousLocation-SurfaceConditionSubCauseCode", "group": 3},
    {"id": "ITS-Container.HazardousLocation-ObstacleOnTheRoadSubCauseCode", "group": 3},
    {"id": "ITS-Container.HazardousLocation-AnimalOnTheRoadSubCauseCode", "group": 3},
    {"id": "ITS-Container.CollisionRiskSubCauseCode", "group": 3},
    {"id": "ITS-Container.SignalViolationSubCauseCode", "group": 3},
    {"id": "ITS-Container.RescueAndRecoveryWorkInProgressSubCauseCode", "group": 3},
    {"id": "ITS-Container.DangerousEndOfQueueSubCauseCode", "group": 3},
    {"id": "ITS-Container.DangerousSituationSubCauseCode", "group": 3},
    {"id": "ITS-Container.VehicleBreakdownSubCauseCode", "group": 3},
    {"id": "ITS-Container.PostCrashSubCauseCode", "group": 3},
    {"id": "ITS-Container.Curvature", "group": 3},
    {"id": "ITS-Container.CurvatureValue", "group": 3},
    {"id": "ITS-Container.CurvatureConfidence", "group": 3},
    {"id": "ITS-Container.CurvatureCalculationMode", "group": 3},
    {"id": "ITS-Container.Heading", "group": 3},
    {"id": "ITS-Container.HeadingValue", "group": 3},
    {"id": "ITS-Container.HeadingConfidence", "group": 3},
    {"id": "ITS-Container.LanePosition", "group": 3},
    {"id": "ITS-Container.ClosedLanes", "group": 3},
    {"id": "ITS-Container.HardShoulderStatus", "group": 3},
    {"id": "ITS-Container.DrivingLaneStatus", "group": 3},
    {"id": "ITS-Container.PerformanceClass", "group": 3},
    {"id": "ITS-Container.SpeedValue", "group": 3},
    {"id": "ITS-Container.SpeedConfidence", "group": 3},
    {"id": "ITS-Container.VehicleMass", "group": 3},
    {"id": "ITS-Container.Speed", "group": 3},
    {"id": "ITS-Container.DriveDirection", "group": 3},
    {"id": "ITS-Container.EmbarkationStatus", "group": 3},
    {"id": "ITS-Container.LongitudinalAcceleration", "group": 3},
    {"id": "ITS-Container.LongitudinalAccelerationValue", "group": 3},
    {"id": "ITS-Container.AccelerationConfidence", "group": 3},
    {"id": "ITS-Container.LateralAcceleration", "group": 3},
    {"id": "ITS-Container.LateralAccelerationValue", "group": 3},
    {"id": "ITS-Container.VerticalAcceleration", "group": 3},
    {"id": "ITS-Container.VerticalAccelerationValue", "group": 3},
    {"id": "ITS-Container.StationType", "group": 3},
    {"id": "ITS-Container.ExteriorLights", "group": 3},
    {"id": "ITS-Container.DangerousGoodsBasic", "group": 3},
    {"id": "ITS-Container.DangerousGoodsExtended", "group": 3},
    {"id": "ITS-Container.SpecialTransportType", "group": 3},
    {"id": "ITS-Container.LightBarSirenInUse", "group": 3},
    {"id": "ITS-Container.HeightLonCarr", "group": 3},
    {"id": "ITS-Container.PosLonCarr", "group": 3},
    {"id": "ITS-Container.PosPillar", "group": 3},
    {"id": "ITS-Container.PosCentMass", "group": 3},
    {"id": "ITS-Container.RequestResponseIndication", "group": 3},
    {"id": "ITS-Container.SpeedLimit", "group": 3},
    {"id": "ITS-Container.StationarySince", "group": 3},
    {"id": "ITS-Container.Temperature", "group": 3},
    {"id": "ITS-Container.TrafficRule", "group": 3},
    {"id": "ITS-Container.WheelBaseVehicle", "group": 3},
    {"id": "ITS-Container.TurningRadius", "group": 3},
    {"id": "ITS-Container.PosFrontAx", "group": 3},
    {"id": "ITS-Container.PositionOfOccupants", "group": 3},
    {"id": "ITS-Container.PositioningSolutionType", "group": 3},
    {"id": "ITS-Container.VehicleIdentification", "group": 3},
    {"id": "ITS-Container.WMInumber", "group": 3},
    {"id": "ITS-Container.VDS", "group": 3},
    {"id": "ITS-Container.EnergyStorageType", "group": 3},
    {"id": "ITS-Container.VehicleLength", "group": 3},
    {"id": "ITS-Container.VehicleLengthValue", "group": 3},
    {"id": "ITS-Container.VehicleLengthConfidenceIndication", "group": 3},
    {"id": "ITS-Container.VehicleWidth", "group": 3},
    {"id": "ITS-Container.PathHistory", "group": 3},
    {"id": "ITS-Container.EmergencyPriority", "group": 3},
    {"id": "ITS-Container.InformationQuality", "group": 3},
    {"id": "ITS-Container.RoadType", "group": 3},
    {"id": "ITS-Container.SteeringWheelAngle", "group": 3},
    {"id": "ITS-Container.SteeringWheelAngleValue", "group": 3},
    {"id": "ITS-Container.SteeringWheelAngleConfidence", "group": 3},
    {"id": "ITS-Container.TimestampIts", "group": 3},
    {"id": "ITS-Container.VehicleRole", "group": 3},
    {"id": "ITS-Container.YawRate", "group": 3},
    {"id": "ITS-Container.YawRateValue", "group": 3},
    {"id": "ITS-Container.YawRateConfidence", "group": 3},
    {"id": "ITS-Container.ProtectedZoneType", "group": 3},
    {"id": "ITS-Container.RelevanceDistance", "group": 3},
    {"id": "ITS-Container.RelevanceTrafficDirection", "group": 3},
    {"id": "ITS-Container.TransmissionInterval", "group": 3},
    {"id": "ITS-Container.ValidityDuration", "group": 3},
    {"id": "ITS-Container.ActionID", "group": 3},
    {"id": "ITS-Container.ItineraryPath", "group": 3},
    {"id": "ITS-Container.ProtectedCommunicationZone", "group": 3},
    {"id": "ITS-Container.Traces", "group": 3},
    {"id": "ITS-Container.NumberOfOccupants", "group": 3},
    {"id": "ITS-Container.SequenceNumber", "group": 3},
    {"id": "ITS-Container.PositionOfPillars", "group": 3},
    {"id": "ITS-Container.RestrictedTypes", "group": 3},
    {"id": "ITS-Container.EventHistory", "group": 3},
    {"id": "ITS-Container.EventPoint", "group": 3},
    {"id": "ITS-Container.ProtectedCommunicationZonesRSU", "group": 3},
    {"id": "ITS-Container.CenDsrcTollingZone", "group": 3},
    {"id": "ITS-Container.ProtectedZoneRadius", "group": 3},
    {"id": "ITS-Container.ProtectedZoneID", "group": 3},
    {"id": "ITS-Container.CenDsrcTollingZoneID", "group": 3},
    {"id": "ITS-Container.DigitalMap", "group": 3},
    {"id": "ITS-Container.OpeningDaysHours", "group": 3},
    {"id": "ITS-Container.PhoneNumber", "group": 3}
  ],
  "links": [
    {"source": "DENM-PDU-Descriptions.DENM", "target": "DENM-PDU-Descriptions.DecentralizedEnvironmentalNotificationMessage", "value": 1},
    {"source": "DENM-PDU-Descriptions.DENM", "target": "ITS-Container.ItsPduHeader", "value": 1},
    {"source": "DENM-PDU-Descriptions.DecentralizedEnvironmentalNotificationMessage", "target": "DENM-PDU-Descriptions.ManagementContainer", "value": 1},
    {"source": "DENM-PDU-Descriptions.DecentralizedEnvironmentalNotificationMessage", "target": "DENM-PDU-Descriptions.LocationContainer", "value": 1},
    {"source": "DENM-PDU-Descriptions.DecentralizedEnvironmentalNotificationMessage", "target": "DENM-PDU-Descriptions.SituationContainer", "value": 1},
    {"source": "DENM-PDU-Descriptions.DecentralizedEnvironmentalNotificationMessage", "target": "DENM-PDU-Descriptions.AlacarteContainer", "value": 1},
    {"source": "DENM-PDU-Descriptions.ManagementContainer", "target": "ITS-Container.TimestampIts", "value": 1},
    {"source": "DENM-PDU-Descriptions.ManagementContainer", "target": "DENM-PDU-Descriptions.Termination", "value": 1},
    {"source": "DENM-PDU-Descriptions.ManagementContainer", "target": "ITS-Container.RelevanceDistance", "value": 1},
    {"source": "DENM-PDU-Descriptions.ManagementContainer", "target": "ITS-Container.TransmissionInterval", "value": 1},
    {"source": "DENM-PDU-Descriptions.ManagementContainer", "target": "ITS-Container.ValidityDuration", "value": 1},
    {"source": "DENM-PDU-Descriptions.ManagementContainer", "target": "ITS-Container.StationType", "value": 1},
    {"source": "DENM-PDU-Descriptions.ManagementContainer", "target": "DENM-PDU-Descriptions.defaultValidity", "value": 1},
    {"source": "DENM-PDU-Descriptions.ManagementContainer", "target": "ITS-Container.ReferencePosition", "value": 1},
    {"source": "DENM-PDU-Descriptions.ManagementContainer", "target": "ITS-Container.ActionID", "value": 1},
    {"source": "DENM-PDU-Descriptions.ManagementContainer", "target": "ITS-Container.RelevanceTrafficDirection", "value": 1},
    {"source": "DENM-PDU-Descriptions.SituationContainer", "target": "ITS-Container.EventHistory", "value": 1},
    {"source": "DENM-PDU-Descriptions.SituationContainer", "target": "ITS-Container.InformationQuality", "value": 1},
    {"source": "DENM-PDU-Descriptions.SituationContainer", "target": "ITS-Container.CauseCode", "value": 1},
    {"source": "DENM-PDU-Descriptions.LocationContainer", "target": "ITS-Container.Traces", "value": 1},
    {"source": "DENM-PDU-Descriptions.LocationContainer", "target": "ITS-Container.Speed", "value": 1},
    {"source": "DENM-PDU-Descriptions.LocationContainer", "target": "ITS-Container.Heading", "value": 1},
    {"source": "DENM-PDU-Descriptions.LocationContainer", "target": "ITS-Container.RoadType", "value": 1},
    {"source": "DENM-PDU-Descriptions.ImpactReductionContainer", "target": "ITS-Container.PositionOfPillars", "value": 1},
    {"source": "DENM-PDU-Descriptions.ImpactReductionContainer", "target": "ITS-Container.PosCentMass", "value": 1},
    {"source": "DENM-PDU-Descriptions.ImpactReductionContainer", "target": "ITS-Container.VehicleMass", "value": 1},
    {"source": "DENM-PDU-Descriptions.ImpactReductionContainer", "target": "ITS-Container.TurningRadius", "value": 1},
    {"source": "DENM-PDU-Descriptions.ImpactReductionContainer", "target": "ITS-Container.PositionOfOccupants", "value": 1},
    {"source": "DENM-PDU-Descriptions.ImpactReductionContainer", "target": "ITS-Container.PosFrontAx", "value": 1},
    {"source": "DENM-PDU-Descriptions.ImpactReductionContainer", "target": "ITS-Container.PosLonCarr", "value": 1},
    {"source": "DENM-PDU-Descriptions.ImpactReductionContainer", "target": "ITS-Container.WheelBaseVehicle", "value": 1},
    {"source": "DENM-PDU-Descriptions.ImpactReductionContainer", "target": "ITS-Container.RequestResponseIndication", "value": 1},
    {"source": "DENM-PDU-Descriptions.ImpactReductionContainer", "target": "ITS-Container.HeightLonCarr", "value": 1},
    {"source": "DENM-PDU-Descriptions.RoadWorksContainerExtended", "target": "ITS-Container.SpeedLimit", "value": 1},
    {"source": "DENM-PDU-Descriptions.RoadWorksContainerExtended", "target": "ITS-Container.DeltaReferencePosition", "value": 1},
    {"source": "DENM-PDU-Descriptions.RoadWorksContainerExtended", "target": "ITS-Container.RestrictedTypes", "value": 1},
    {"source": "DENM-PDU-Descriptions.RoadWorksContainerExtended", "target": "ITS-Container.ItineraryPath", "value": 1},
    {"source": "DENM-PDU-Descriptions.RoadWorksContainerExtended", "target": "ITS-Container.LightBarSirenInUse", "value": 1},
    {"source": "DENM-PDU-Descriptions.RoadWorksContainerExtended", "target": "ITS-Container.TrafficRule", "value": 1},
    {"source": "DENM-PDU-Descriptions.RoadWorksContainerExtended", "target": "DENM-PDU-Descriptions.ReferenceDenms", "value": 1},
    {"source": "DENM-PDU-Descriptions.RoadWorksContainerExtended", "target": "ITS-Container.ClosedLanes", "value": 1},
    {"source": "DENM-PDU-Descriptions.RoadWorksContainerExtended", "target": "ITS-Container.CauseCode", "value": 1},
    {"source": "DENM-PDU-Descriptions.StationaryVehicleContainer", "target": "ITS-Container.EnergyStorageType", "value": 1},
    {"source": "DENM-PDU-Descriptions.StationaryVehicleContainer", "target": "ITS-Container.NumberOfOccupants", "value": 1},
    {"source": "DENM-PDU-Descriptions.StationaryVehicleContainer", "target": "ITS-Container.DangerousGoodsExtended", "value": 1},
    {"source": "DENM-PDU-Descriptions.StationaryVehicleContainer", "target": "ITS-Container.VehicleIdentification", "value": 1},
    {"source": "DENM-PDU-Descriptions.StationaryVehicleContainer", "target": "ITS-Container.StationarySince", "value": 1},
    {"source": "DENM-PDU-Descriptions.StationaryVehicleContainer", "target": "ITS-Container.CauseCode", "value": 1},
    {"source": "DENM-PDU-Descriptions.AlacarteContainer", "target": "ITS-Container.PositioningSolutionType", "value": 1},
    {"source": "DENM-PDU-Descriptions.AlacarteContainer", "target": "DENM-PDU-Descriptions.StationaryVehicleContainer", "value": 1},
    {"source": "DENM-PDU-Descriptions.AlacarteContainer", "target": "ITS-Container.Temperature", "value": 1},
    {"source": "DENM-PDU-Descriptions.AlacarteContainer", "target": "DENM-PDU-Descriptions.ImpactReductionContainer", "value": 1},
    {"source": "DENM-PDU-Descriptions.AlacarteContainer", "target": "DENM-PDU-Descriptions.RoadWorksContainerExtended", "value": 1},
    {"source": "DENM-PDU-Descriptions.AlacarteContainer", "target": "ITS-Container.LanePosition", "value": 1},
    {"source": "DENM-PDU-Descriptions.ReferenceDenms", "target": "ITS-Container.ActionID", "value": 1},
    {"source": "ITS-Container.ItsPduHeader", "target": "ITS-Container.StationID", "value": 1},
    {"source": "ITS-Container.ReferencePosition", "target": "ITS-Container.Latitude", "value": 1},
    {"source": "ITS-Container.ReferencePosition", "target": "ITS-Container.Longitude", "value": 1},
    {"source": "ITS-Container.ReferencePosition", "target": "ITS-Container.PosConfidenceEllipse", "value": 1},
    {"source": "ITS-Container.ReferencePosition", "target": "ITS-Container.Altitude", "value": 1},
    {"source": "ITS-Container.DeltaReferencePosition", "target": "ITS-Container.DeltaLongitude", "value": 1},
    {"source": "ITS-Container.DeltaReferencePosition", "target": "ITS-Container.DeltaAltitude", "value": 1},
    {"source": "ITS-Container.DeltaReferencePosition", "target": "ITS-Container.DeltaLatitude", "value": 1},
    {"source": "ITS-Container.Altitude", "target": "ITS-Container.AltitudeValue", "value": 1},
    {"source": "ITS-Container.Altitude", "target": "ITS-Container.AltitudeConfidence", "value": 1},
    {"source": "ITS-Container.PosConfidenceEllipse", "target": "ITS-Container.HeadingValue", "value": 1},
    {"source": "ITS-Container.PosConfidenceEllipse", "target": "ITS-Container.SemiAxisLength", "value": 1},
    {"source": "ITS-Container.PathPoint", "target": "ITS-Container.PathDeltaTime", "value": 1},
    {"source": "ITS-Container.PathPoint", "target": "ITS-Container.DeltaReferencePosition", "value": 1},
    {"source": "ITS-Container.PtActivation", "target": "ITS-Container.PtActivationData", "value": 1},
    {"source": "ITS-Container.PtActivation", "target": "ITS-Container.PtActivationType", "value": 1},
    {"source": "ITS-Container.CauseCode", "target": "ITS-Container.SubCauseCodeType", "value": 1},
    {"source": "ITS-Container.CauseCode", "target": "ITS-Container.CauseCodeType", "value": 1},
    {"source": "ITS-Container.Curvature", "target": "ITS-Container.CurvatureConfidence", "value": 1},
    {"source": "ITS-Container.Curvature", "target": "ITS-Container.CurvatureValue", "value": 1},
    {"source": "ITS-Container.Heading", "target": "ITS-Container.HeadingValue", "value": 1},
    {"source": "ITS-Container.Heading", "target": "ITS-Container.HeadingConfidence", "value": 1},
    {"source": "ITS-Container.ClosedLanes", "target": "ITS-Container.DrivingLaneStatus", "value": 1},
    {"source": "ITS-Container.ClosedLanes", "target": "ITS-Container.HardShoulderStatus", "value": 1},
    {"source": "ITS-Container.Speed", "target": "ITS-Container.SpeedValue", "value": 1},
    {"source": "ITS-Container.Speed", "target": "ITS-Container.SpeedConfidence", "value": 1},
    {"source": "ITS-Container.LongitudinalAcceleration", "target": "ITS-Container.LongitudinalAccelerationValue", "value": 1},
    {"source": "ITS-Container.LongitudinalAcceleration", "target": "ITS-Container.AccelerationConfidence", "value": 1},
    {"source": "ITS-Container.LateralAcceleration", "target": "ITS-Container.LateralAccelerationValue", "value": 1},
    {"source": "ITS-Container.LateralAcceleration", "target": "ITS-Container.AccelerationConfidence", "value": 1},
    {"source": "ITS-Container.VerticalAcceleration", "target": "ITS-Container.VerticalAccelerationValue", "value": 1},
    {"source": "ITS-Container.VerticalAcceleration", "target": "ITS-Container.AccelerationConfidence", "value": 1},
    {"source": "ITS-Container.DangerousGoodsExtended", "target": "ITS-Container.DangerousGoodsBasic", "value": 1},
    {"source": "ITS-Container.DangerousGoodsExtended", "target": "ITS-Container.PhoneNumber", "value": 1},
    {"source": "ITS-Container.VehicleIdentification", "target": "ITS-Container.VDS", "value": 1},
    {"source": "ITS-Container.VehicleIdentification", "target": "ITS-Container.WMInumber", "value": 1},
    {"source": "ITS-Container.VehicleLength", "target": "ITS-Container.VehicleLengthValue", "value": 1},
    {"source": "ITS-Container.VehicleLength", "target": "ITS-Container.VehicleLengthConfidenceIndication", "value": 1},
    {"source": "ITS-Container.PathHistory", "target": "ITS-Container.PathPoint", "value": 1},
    {"source": "ITS-Container.SteeringWheelAngle", "target": "ITS-Container.SteeringWheelAngleConfidence", "value": 1},
    {"source": "ITS-Container.SteeringWheelAngle", "target": "ITS-Container.SteeringWheelAngleValue", "value": 1},
    {"source": "ITS-Container.YawRate", "target": "ITS-Container.YawRateValue", "value": 1},
    {"source": "ITS-Container.YawRate", "target": "ITS-Container.YawRateConfidence", "value": 1},
    {"source": "ITS-Container.ActionID", "target": "ITS-Container.StationID", "value": 1},
    {"source": "ITS-Container.ActionID", "target": "ITS-Container.SequenceNumber", "value": 1},
    {"source": "ITS-Container.ItineraryPath", "target": "ITS-Container.ReferencePosition", "value": 1},
    {"source": "ITS-Container.ProtectedCommunicationZone", "target": "ITS-Container.ProtectedZoneType", "value": 1},
    {"source": "ITS-Container.ProtectedCommunicationZone", "target": "ITS-Container.ProtectedZoneID", "value": 1},
    {"source": "ITS-Container.ProtectedCommunicationZone", "target": "ITS-Container.TimestampIts", "value": 1},
    {"source": "ITS-Container.ProtectedCommunicationZone", "target": "ITS-Container.Latitude", "value": 1},
    {"source": "ITS-Container.ProtectedCommunicationZone", "target": "ITS-Container.Longitude", "value": 1},
    {"source": "ITS-Container.ProtectedCommunicationZone", "target": "ITS-Container.ProtectedZoneRadius", "value": 1},
    {"source": "ITS-Container.Traces", "target": "ITS-Container.PathHistory", "value": 1},
    {"source": "ITS-Container.PositionOfPillars", "target": "ITS-Container.PosPillar", "value": 1},
    {"source": "ITS-Container.RestrictedTypes", "target": "ITS-Container.StationType", "value": 1},
    {"source": "ITS-Container.EventHistory", "target": "ITS-Container.EventPoint", "value": 1},
    {"source": "ITS-Container.EventPoint", "target": "ITS-Container.PathDeltaTime", "value": 1},
    {"source": "ITS-Container.EventPoint", "target": "ITS-Container.DeltaReferencePosition", "value": 1},
    {"source": "ITS-Container.EventPoint", "target": "ITS-Container.InformationQuality", "value": 1},
    {"source": "ITS-Container.ProtectedCommunicationZonesRSU", "target": "ITS-Container.ProtectedCommunicationZone", "value": 1},
    {"source": "ITS-Container.CenDsrcTollingZone", "target": "ITS-Container.Latitude", "value": 1},
    {"source": "ITS-Container.CenDsrcTollingZone", "target": "ITS-Container.Longitude", "value": 1},
    {"source": "ITS-Container.CenDsrcTollingZone", "target": "ITS-Container.CenDsrcTollingZoneID", "value": 1},
    {"source": "ITS-Container.CenDsrcTollingZoneID", "target": "ITS-Container.ProtectedZoneID", "value": 1},
    {"source": "ITS-Container.DigitalMap", "target": "ITS-Container.ReferencePosition", "value": 1}
  ]
}
